PyMySQLLock/__init__.py
PyMySQLLock/connection_factory.py
PyMySQLLock/lock.py
PyMySQLLock/locker.py
PyMySQLLock-0.2.0.dist-info/LICENSE
PyMySQLLock-0.2.0.dist-info/METADATA
PyMySQLLock-0.2.0.dist-info/WHEEL
PyMySQLLock-0.2.0.dist-info/top_level.txt
PyMySQLLock-0.2.0.dist-info/RECORD
