Metadata-Version: 2.1
Name: PyMySQLLock
Version: 0.2.0
Summary: MySQL Backed Locking Primitive
Home-page: https://github.com/sanketplus/PyMySQLLock
Author: Sanket Patel
Author-email: sanketplus@gmail.com
License: MIT license
Keywords: PyMySQLLock
Platform: UNKNOWN
Classifier: Development Status :: 2 - Pre-Alpha
Classifier: Intended Audience :: Developers
Classifier: License :: OSI Approved :: MIT License
Classifier: Natural Language :: English
Classifier: Programming Language :: Python :: 3
Classifier: Programming Language :: Python :: 3.6
Classifier: Programming Language :: Python :: 3.7
Classifier: Programming Language :: Python :: 3.8
Requires-Python: >=3.5
